pyvpm.py
pyvpm-0.0.2.dist-info/METADATA
pyvpm-0.0.2.dist-info/WHEEL
pyvpm-0.0.2.dist-info/top_level.txt
pyvpm-0.0.2.dist-info/RECORD
