Metadata-Version: 2.1
Name: pyvpm
Version: 0.0.2
Summary: Virtual Product Mnanagement for Python
Home-page: https://github.com/arielden/pyvpm
Author: Ariel Denaro
Classifier: License :: OSI Approved :: MIT License
Classifier: Programming Language :: Python :: 3
Classifier: Programming Language :: Python :: 3.10
